package_backup/__init__.py
package_backup/simple_greet.py
script_testing/__init__.py
script_testing/simple_greet.py
script_testing-0.1.1.dist-info/METADATA
script_testing-0.1.1.dist-info/WHEEL
script_testing-0.1.1.dist-info/top_level.txt
script_testing-0.1.1.dist-info/RECORD
