Metadata-Version: 2.4
Name: script_testing
Version: 0.1.1
Summary: A simple Python package for greeting
Classifier: Programming Language :: Python :: 3
Classifier: License :: OSI Approved :: MIT License
Classifier: Operating System :: OS Independent
Requires-Python: >=3.6
Requires-Dist: twine
Requires-Dist: build
Dynamic: classifier
Dynamic: requires-dist
Dynamic: requires-python
Dynamic: summary
